LICENSE
README.md
setup.py
vc_algo/__init__.py
vc_algo.egg-info/PKG-INFO
vc_algo.egg-info/SOURCES.txt
vc_algo.egg-info/dependency_links.txt
vc_algo.egg-info/top_level.txt
vc_algo/algorithm/__init__.py
vc_algo/algorithm/classfication/__init__.py
vc_algo/algorithm/others/__init__.py
vc_algo/algorithm/others/template.py
vc_algo/algorithm/regression/__init__.py
vc_algo/algorithm/regression/lr.py
vc_algo/algorithm/simple/__init__.py
vc_algo/analysis/__init__.py
vc_algo/data_loader/__init__.py
vc_algo/example/__init__.py
vc_algo/example/factor/1max_ic_ir.py
vc_algo/example/factor/__init__.py
vc_algo/example/pipeline/1basic_sklearn.py
vc_algo/example/pipeline/2extend_transformer.py
vc_algo/example/pipeline/3extend_algorithm.py
vc_algo/example/pipeline/__init__.py
vc_algo/preprocess/__init__.py
vc_algo/preprocess/filter/__init__.py
vc_algo/preprocess/filter/columns.py
vc_algo/preprocess/imputor/__init__.py
vc_algo/preprocess/ohters/__init__.py
vc_algo/preprocess/ohters/iv.py
vc_algo/preprocess/scaler/__init__.py
vc_algo/preprocess/winsorizor/__init__.py
vc_algo/tools/__init__.py
vc_algo/tools/factor_filter/__init__.py
vc_algo/tools/factor_filter/ic_ir.py