Metadata-Version: 2.1
Name: vc-algo
Version: 1.1
Summary: 维C算法工具包
Home-page: UNKNOWN
Author: Frank
Author-email: frank@vc.com
License: vc-private
Platform: UNKNOWN
Classifier: Programming Language :: Python :: 3.8
Classifier: Operating System :: OS Independent
License-File: LICENSE
